Topsis_Sahil_102003466/__init__.py
Topsis_Sahil_102003466/__main__.py
Topsis_Sahil_102003466-1.0.0.dist-info/LICENSE
Topsis_Sahil_102003466-1.0.0.dist-info/METADATA
Topsis_Sahil_102003466-1.0.0.dist-info/WHEEL
Topsis_Sahil_102003466-1.0.0.dist-info/entry_points.txt
Topsis_Sahil_102003466-1.0.0.dist-info/top_level.txt
Topsis_Sahil_102003466-1.0.0.dist-info/RECORD
