Metadata-Version: 2.1
Name: Topsis-Sahil-102003466
Version: 1.0.0
Summary: TOPSIS is a practical and useful technique for ranking and selection of a number of externally determined alternatives through distance measures.
Home-page: https://github.com/sahilkadiyan/Topsis-Sahil-102003466.git
Author: Sahil Kadiyan
Author-email: kadiyans990@gmail.com
License: MIT
Platform: UNKNOWN
Classifier: License :: OSI Approved :: MIT License
Classifier: Programming Language :: Python :: 3.6
Classifier: Programming Language :: Python :: 3.7
Classifier: Programming Language :: Python :: 3.8
